{
  "minecraft:recipes/misc/charcoal": {
    "criteria": {
      "has_log": "2019-05-05 01:43:24 -0600"
    },
    "done": true
  },
  "minecraft:recipes/transportation/acacia_boat": {
    "criteria": {
      "in_water": "2019-05-05 01:40:29 -0600"
    },
    "done": true
  },
  "minecraft:recipes/transportation/oak_boat": {
    "criteria": {
      "in_water": "2019-05-05 01:40:29 -0600"
    },
    "done": true
  },
  "minecraft:recipes/building_blocks/oak_planks": {
    "criteria": {
      "has_log": "2019-05-05 01:43:24 -0600"
    },
    "done": true
  },
  "minecraft:recipes/transportation/dark_oak_boat": {
    "criteria": {
      "in_water": "2019-05-05 01:40:29 -0600"
    },
    "done": true
  },
  "minecraft:recipes/transportation/birch_boat": {
    "criteria": {
      "in_water": "2019-05-05 01:40:29 -0600"
    },
    "done": true
  },
  "minecraft:recipes/transportation/jungle_boat": {
    "criteria": {
      "in_water": "2019-05-05 01:40:29 -0600"
    },
    "done": true
  },
  "minecraft:recipes/transportation/spruce_boat": {
    "criteria": {
      "in_water": "2019-05-05 01:40:29 -0600"
    },
    "done": true
  },
  "minecraft:recipes/building_blocks/oak_wood": {
    "criteria": {
      "has_log": "2019-05-05 01:43:24 -0600"
    },
    "done": true
  },
  "minecraft:adventure/adventuring_time": {
    "criteria": {
      "minecraft:forest": "2019-05-05 01:40:21 -0600",
      "minecraft:beach": "2019-05-05 01:40:49 -0600",
      "minecraft:river": "2019-05-05 01:40:32 -0600",
      "minecraft:wooded_hills": "2019-05-05 01:41:19 -0600"
    },
    "done": false
  },
  "DataVersion": 1952
}